{"http://www.openlinksw.com/schemas/virtrdf#array-of-QuadMapFormat": [], "http://rdfs.org/ns/void#Dataset": [{"": "2"}], "http://www.w3.org/2002/07/owl#Class": [{"": "2"}], "http://www.openlinksw.com/schemas/virtrdf#QuadMapValue": [], "http://www.openlinksw.com/schemas/virtrdf#QuadMapFormat": [], "http://www.openlinksw.com/schemas/virtrdf#QuadMap": [], "http://www.openlinksw.com/schemas/virtrdf#array-of-QuadMap": [], "http://www.w3.org/2000/01/rdf-schema#Class": [{"": "15"}], "http://bio2rdf.org/affymetrix_vocabulary:Probeset": [{"": "1766999"}], "http://www.w3.org/2002/07/owl#Ontology": [], "http://www.openlinksw.com/schemas/virtrdf#QuadMapFText": [], "http://www.openlinksw.com/schemas/virtrdf#array-of-string": [], "http://www.openlinksw.com/schemas/virtrdf#QuadMapATable": [], "http://www.openlinksw.com/schemas/virtrdf#array-of-QuadMapColumn": [], "http://www.w3.org/2002/07/owl#OntologyProperty": [{"": "4"}], "http://www.openlinksw.com/schemas/virtrdf#array-of-QuadMapATable": [], "http://www.w3.org/ns/sparql-service-description#Service": [], "http://www.w3.org/2002/07/owl#AnnotationProperty": [{"": "1"}], "http://bio2rdf.org/dataset_vocabulary:Endpoint": [{"": "1"}], "http://www.openlinksw.com/schemas/virtrdf#QuadMapColumn": [], "http://www.openlinksw.com/schemas/virtrdf#QuadStorage": [], "http://www.w3.org/1999/02/22-rdf-syntax-ns#Property": [{"": "23"}]}